odoo/addons/stock_vertical_lift_empty_tray_check/README.rst
odoo/addons/stock_vertical_lift_empty_tray_check/__init__.py
odoo/addons/stock_vertical_lift_empty_tray_check/__manifest__.py
odoo/addons/stock_vertical_lift_empty_tray_check/i18n/it.po
odoo/addons/stock_vertical_lift_empty_tray_check/i18n/stock_vertical_lift_empty_tray_check.pot
odoo/addons/stock_vertical_lift_empty_tray_check/models/__init__.py
odoo/addons/stock_vertical_lift_empty_tray_check/models/res_config_settings.py
odoo/addons/stock_vertical_lift_empty_tray_check/models/vertical_lift_operation_pick.py
odoo/addons/stock_vertical_lift_empty_tray_check/models/vertical_lift_operation_pick_zero_check.py
odoo/addons/stock_vertical_lift_empty_tray_check/readme/CONFIGURE.md
odoo/addons/stock_vertical_lift_empty_tray_check/readme/CONTRIBUTORS.md
odoo/addons/stock_vertical_lift_empty_tray_check/readme/DESCRIPTION.md
odoo/addons/stock_vertical_lift_empty_tray_check/security/ir.model.access.csv
odoo/addons/stock_vertical_lift_empty_tray_check/static/description/icon.png
odoo/addons/stock_vertical_lift_empty_tray_check/static/description/index.html
odoo/addons/stock_vertical_lift_empty_tray_check/static/src/scss/vertical_lift.scss
odoo/addons/stock_vertical_lift_empty_tray_check/tests/__init__.py
odoo/addons/stock_vertical_lift_empty_tray_check/tests/test_pick.py
odoo/addons/stock_vertical_lift_empty_tray_check/views/res_config_setting_views.xml
odoo/addons/stock_vertical_lift_empty_tray_check/views/vertical_lift_operation_pick_zero_check_views.xml
odoo_addon_stock_vertical_lift_empty_tray_check-18.0.1.0.0.5.dist-info/METADATA
odoo_addon_stock_vertical_lift_empty_tray_check-18.0.1.0.0.5.dist-info/WHEEL
odoo_addon_stock_vertical_lift_empty_tray_check-18.0.1.0.0.5.dist-info/top_level.txt
odoo_addon_stock_vertical_lift_empty_tray_check-18.0.1.0.0.5.dist-info/RECORD
